{"is_source_file": true, "format": "md", "description": ".md file: README.md", "external_files": [], "external_methods": [], "published": [], "classes": [], "methods": [], "calls": [], "search-terms": ["README.md", "md"], "state": 2, "file_id": 1, "knowledge_revision": 37, "git_revision": "b7a2bda9451574ccb79d96785868033b6690fb76", "revision_history": [{"15": "b7a2bda9451574ccb79d96785868033b6690fb76"}, {"37": "b7a2bda9451574ccb79d96785868033b6690fb76"}], "filename": "README.md", "format-version": 4, "code-base-name": "https://github.com/kavia-common/enterprise-dashboard-project-50168-50283.git:kavia-main"}